myapp/__init__.py
myapp/example1.py
myapp/example2.py
myapp/example3.py
myapp/example4.py
myapp/example5.py
myapp/data_subdir/binfile.dat
myapp/data_subdir/textfile.txt
myapp/data_subpackage/__init__.py
myapp/data_subpackage/binfile.dat
myapp/data_subpackage/textfile.txt
resources_example-0.2.dist-info/METADATA
resources_example-0.2.dist-info/WHEEL
resources_example-0.2.dist-info/entry_points.txt
resources_example-0.2.dist-info/top_level.txt
resources_example-0.2.dist-info/RECORD
