Metadata-Version: 2.1
Name: resources-example
Version: 0.2
Summary: An example project demonstrating various ways to access data files in Python package
Home-page: https://github.com/wimglenn/resources-example
Author: Wim Glenn
Author-email: hey@wimglenn.com
License: MIT
Project-URL: Issue Tracker, https://github.com/wimglenn/resources-example/issues
Keywords: packaging,resources
Platform: UNKNOWN
Classifier: Intended Audience :: Developers
Classifier: License :: OSI Approved :: MIT License
Classifier: Operating System :: OS Independent
Classifier: Programming Language :: Python :: 2
Classifier: Programming Language :: Python :: 3
Classifier: Topic :: Software Development :: Libraries :: Python Modules
Classifier: Topic :: System :: Archiving :: Packaging
Classifier: Topic :: System :: Systems Administration
Classifier: Topic :: Utilities
Requires-Dist: setuptools
Requires-Dist: importlib-resources
